odoo/addons/stock_move_packaging_qty/README.rst
odoo/addons/stock_move_packaging_qty/__init__.py
odoo/addons/stock_move_packaging_qty/__manifest__.py
odoo/addons/stock_move_packaging_qty/hooks.py
odoo/addons/stock_move_packaging_qty/i18n/es.po
odoo/addons/stock_move_packaging_qty/i18n/it.po
odoo/addons/stock_move_packaging_qty/i18n/stock_move_packaging_qty.pot
odoo/addons/stock_move_packaging_qty/migrations/18.0.0/pre-migrate.py
odoo/addons/stock_move_packaging_qty/models/__init__.py
odoo/addons/stock_move_packaging_qty/models/stock_move.py
odoo/addons/stock_move_packaging_qty/models/stock_move_line.py
odoo/addons/stock_move_packaging_qty/readme/CONTRIBUTORS.md
odoo/addons/stock_move_packaging_qty/readme/DESCRIPTION.md
odoo/addons/stock_move_packaging_qty/readme/ROADMAP.md
odoo/addons/stock_move_packaging_qty/static/description/icon.png
odoo/addons/stock_move_packaging_qty/static/description/index.html
odoo/addons/stock_move_packaging_qty/tests/__init__.py
odoo/addons/stock_move_packaging_qty/tests/test_stock_move_packaging_qty.py
odoo/addons/stock_move_packaging_qty/views/report_stock_picking.xml
odoo/addons/stock_move_packaging_qty/views/stock_move_line_view.xml
odoo/addons/stock_move_packaging_qty/views/stock_move_view.xml
odoo/addons/stock_move_packaging_qty/views/stock_picking_view.xml
odoo_addon_stock_move_packaging_qty-18.0.1.1.0.dist-info/METADATA
odoo_addon_stock_move_packaging_qty-18.0.1.1.0.dist-info/WHEEL
odoo_addon_stock_move_packaging_qty-18.0.1.1.0.dist-info/top_level.txt
odoo_addon_stock_move_packaging_qty-18.0.1.1.0.dist-info/RECORD
