Metadata-Version: 2.1
Name: odoo-addon-stock_move_packaging_qty
Version: 18.0.1.1.0
Requires-Python: >=3.10
Requires-Dist: odoo==18.0.*
Summary: Add packaging fields in the stock moves
Home-page: https://github.com/OCA/stock-logistics-warehouse
License: LGPL-3
Author: ForgeFlow, Moduon, Odoo Community Association (OCA)
Author-email: support@odoo-community.org
Classifier: Programming Language :: Python
Classifier: Framework :: Odoo
Classifier: Framework :: Odoo :: 18.0
Classifier: License :: OSI Approved :: GNU Lesser General Public License v3 (LGPLv3)
